<?xml version="1.0" encoding="utf-8"?>
<odoo>
    <record id="roi_default_form_view" model="ir.ui.view">
        <field name="active" eval="True"/>
        <field name="arch" type="xml">
            <form>
                <sheet>
                    <h1>
                        <field name="name" required="1"/>
                    </h1>
                    <group name="roi_group">
                        <group>
                            <field name="partner_id" required="1"/>
                            <field name="user_id"/>
                            <field name="balance_today" widget="monetary"/>
                        </group>
                        <group>
                            <field name="date_start" required="1"/>
                            <field name="date_end"/>
                            <field name="date_roi"/>
                        </group>
                    </group>
                    <group>
                        <field name="set_id" attrs="{'invisible':[('date_start','=',False)]}"/>
                    </group>
                    <field name="line_ids" context="{'default_qty':1, 'default_currency_id':1, 'default_date_init':date_start}" attrs="{'invisible':[('date_start','=',False)]}">
                        <tree editable="bottom">
                            <field name="sequence" widget="handle"/>
                            <field name="name" required="1"/>
                            <field name="date_init"/>
                            <field name="qty" required="1"/>
                            <field name="amount" required="1" widget="monetary"/>
                            <field name="type" required="1"/>
                            <field name="agregate" widget="monetary"/>
                            <field name="currency_id" invisible="1"/>
                            <field name="roi_id" invisible="1"/>
                        </tree>
                    </field>
                    <group name="roi_links" col="4">
                        <field name="sale_id"/>
                        <field name="contract_id"/>
                    </group>
                    <group name="roi_modification_data" col="4">
                        <field name="create_date"/>
                        <field name="create_uid"/>
                        <field name="write_date"/>
                        <field name="create_uid"/>
                        <field name="currency_id" invisible="1"/>
                    </group>
                </sheet>
            </form>
        </field>
        <field name="field_parent" eval="False"/>
        <field name="groups_id" eval="[(6, 0, [])]"/>
        <field name="inherit_id" eval="False"/>
        <field name="key" eval="False"/>
        <field name="mode">primary</field>
        <field name="model">roi</field>
        <field name="name">Default form view for ROI</field>
        <field name="priority">16</field>
        <field name="type">form</field>
    </record>

    <record id="roi_tree" model="ir.ui.view">
        <field name="active" eval="True"/>
        <field name="arch" type="xml">
            <tree>
                <field name="name"/>
                <field name="partner_id"/>
                <field name="date_start"/>
                <field name="date_end"/>
                <field name="balance_today" widget="monetary"/>
                <field name="date_roi"/>
            </tree>
        </field>
        <field name="field_parent" eval="False"/>
        <field name="groups_id" eval="[(6, 0, [])]"/>
        <field name="inherit_id" eval="False"/>
        <field name="key" eval="False"/>
        <field name="mode">primary</field>
        <field name="model">roi</field>
        <field name="name">Default tree view for ROI</field>
        <field name="priority">16</field>
        <field name="type">tree</field>
    </record>

</odoo>
